game_metr_analyzer/__init__.py
game_metr_analyzer/main.py
game_metr_analyzer/prompts.py
game_metr_analyzer-2025.12.21162154.dist-info/METADATA
game_metr_analyzer-2025.12.21162154.dist-info/WHEEL
game_metr_analyzer-2025.12.21162154.dist-info/top_level.txt
game_metr_analyzer-2025.12.21162154.dist-info/RECORD
