Metadata-Version: 2.4
Name: game-metr-analyzer
Version: 2025.12.21162154
Summary: A new package would help users analyze and interpret game narratives or story structures, specifically focusing on the METR (Mechanics, Esthetics, Technology, and Rhetoric) plot framework used in game
Author-email: game-metr-analyzer <hi@eugene.plus>
License: MIT
Project-URL: Homepage, https://github.com/chigwell/game-metr-analyzer
Requires-Python: >=3.9
Requires-Dist: langchain-llm7>=0.0.0
Requires-Dist: llmatch-messages>=0.0.0
Requires-Dist: langchain-core>=0.3.0
